electroblocks/__init__.py
electroblocks/core.py
electroblocks-0.1.24.dist-info/licenses/LICENSE
electroblocks-0.1.24.dist-info/METADATA
electroblocks-0.1.24.dist-info/WHEEL
electroblocks-0.1.24.dist-info/top_level.txt
electroblocks-0.1.24.dist-info/RECORD
