Metadata-Version: 2.4
Name: electroblocks
Version: 0.1.24
Summary: Python client library to interact with ElectroBlocks Arduino firmware
Home-page: https://github.com/yourusername/electroblocks
Author: Your Name
Author-email: Noah Glaser <glaserpower@gmail.com>
License: GNU v3.0
Project-URL: Homepage, https://github.com/ElectroBlocks/python
Requires-Python: >=3.6
License-File: LICENSE
Requires-Dist: pyserial
Dynamic: author
Dynamic: home-page
Dynamic: license-file
Dynamic: requires-python
